sotag/__init__.py
sotag/cli.py
sotag/sotag.py
sotag/utils.py
sotag/download/__init__.py
sotag/download/sotag_downloader.py
sotag/download/stackoverflow.com-Tags.zip
sotag/models/__init__.py
sotag/models/tag.py
sotag-0.1.1.dist-info/AUTHORS.rst
sotag-0.1.1.dist-info/LICENSE
sotag-0.1.1.dist-info/METADATA
sotag-0.1.1.dist-info/WHEEL
sotag-0.1.1.dist-info/entry_points.txt
sotag-0.1.1.dist-info/top_level.txt
sotag-0.1.1.dist-info/RECORD
