Metadata-Version: 2.1
Name: sotag
Version: 0.1.1
Summary: provide a wrapper to access Stack Overflow tag data.
Home-page: https://github.com/FudanSELab/sotag
Author: Software Engineering Laboratory of Fudan University
Author-email: lmwtclmwtc@outlook.com
License: MIT license
Keywords: sotag
Platform: UNKNOWN
Classifier: Development Status :: 2 - Pre-Alpha
Classifier: Intended Audience :: Developers
Classifier: License :: OSI Approved :: MIT License
Classifier: Natural Language :: English
Classifier: Programming Language :: Python :: 3
Classifier: Programming Language :: Python :: 3.6
Classifier: Programming Language :: Python :: 3.7
Classifier: Programming Language :: Python :: 3.8
Requires-Python: >=3.6
Requires-Dist: Click (>=7.0)
Requires-Dist: numpy (>=1.18)
Requires-Dist: scipy (>=1.4.0)
Requires-Dist: smart-open
Requires-Dist: requests
Requires-Dist: bs4
